README.md
setup.py
minadb/__init__.py
minadb/cli.py
minadb/client.py
minadb/device.py
minadb/utils.py
minadb.egg-info/PKG-INFO
minadb.egg-info/SOURCES.txt
minadb.egg-info/dependency_links.txt
minadb.egg-info/entry_points.txt
minadb.egg-info/top_level.txt