Metadata-Version: 1.1
Name: minadb
Version: 0.4.3
Summary: min adb client implemented with subprocess, nothing special but useful and stable.
Home-page: https://github.com/williamfzc/minadb
Author: williamfzc
Author-email: fengzc@vip.qq.com
License: MIT
Platform: UNKNOWN
Classifier: License :: OSI Approved :: MIT License
Classifier: Programming Language :: Python
Classifier: Programming Language :: Python :: 3
